pandaslearn/__init__.py
pandaslearn/column_transformer.py
pandaslearn/column_transformer_deprecated.py
pandaslearn/dataset.py
pandaslearn/definitions.py
pandaslearn/loguru_handler.py
pandaslearn/model.py
pandaslearn/model_ensemble.py
pandaslearn/model_stack.py
pandaslearn/pandas_learn_deprecated.py
pandaslearn/timeseries.py
pandaslearn/trainer.py
pandaslearn-0.1.9.dist-info/WHEEL
pandaslearn-0.1.9.dist-info/METADATA
pandaslearn-0.1.9.dist-info/RECORD
